markdown_aafigure/__init__.py
markdown_aafigure/extension.py
markdown_aafigure-202405.1012.dist-info/LICENSE
markdown_aafigure-202405.1012.dist-info/METADATA
markdown_aafigure-202405.1012.dist-info/WHEEL
markdown_aafigure-202405.1012.dist-info/entry_points.txt
markdown_aafigure-202405.1012.dist-info/top_level.txt
markdown_aafigure-202405.1012.dist-info/zip-safe
markdown_aafigure-202405.1012.dist-info/RECORD
