Metadata-Version: 2.1
Name: markdown_aafigure
Version: 202405.1012
Summary: aafigure extension for Python Markdown
Home-page: https://gitlab.com/mbarkhau/markdown_aafigure
Author: Manuel Barkhau
Author-email: mbarkhau@gmail.com
License: MIT
Keywords: markdown aafigure extension
Classifier: Development Status :: 5 - Production/Stable
Classifier: Environment :: Console
Classifier: Environment :: Other Environment
Classifier: Intended Audience :: Developers
Classifier: License :: OSI Approved :: MIT License
Classifier: Operating System :: Unix
Classifier: Operating System :: POSIX
Classifier: Operating System :: MacOS :: MacOS X
Classifier: Operating System :: Microsoft :: Windows
Classifier: Programming Language :: Python
Classifier: Programming Language :: Python :: 2.7
Classifier: Programming Language :: Python :: 3
Classifier: Programming Language :: Python :: Implementation :: CPython
Classifier: Programming Language :: Python :: Implementation :: PyPy
Classifier: Topic :: Software Development :: Libraries
Classifier: Topic :: Software Development :: Libraries :: Python Modules
License-File: LICENSE
Requires-Dist: aafigure
Requires-Dist: typing ; python_version < "3.5"
Requires-Dist: Markdown <3.3,>=3.0 ; python_version < "3.6"
Requires-Dist: Markdown >=3.0 ; python_version >= "3.6"
